khodnevis/__init__.py
khodnevis/dictionary.py
khodnevis/emoji_remover.py
khodnevis/normalizer.py
khodnevis/normalizer_utils.py
khodnevis/regexes/__init__.py
khodnevis/regexes/currency.py
khodnevis/regexes/email.py
khodnevis/regexes/latin.py
khodnevis/regexes/number.py
khodnevis/regexes/persian.py
khodnevis/regexes/phone.py
khodnevis/regexes/punk.py
khodnevis/regexes/quote.py
khodnevis/regexes/url.py
khodnevis/vidstream/__init__.py
khodnevis/vidstream/audio.py
khodnevis/vidstream/streaming.py
khodnevis-0.0.2.dist-info/METADATA
khodnevis-0.0.2.dist-info/WHEEL
khodnevis-0.0.2.dist-info/top_level.txt
khodnevis-0.0.2.dist-info/RECORD
